nonebot_plugin_simple_block/__init__.py
nonebot_plugin_simple_block/config.py
nonebot_plugin_simple_block-1.0.1.dist-info/WHEEL
nonebot_plugin_simple_block-1.0.1.dist-info/METADATA
nonebot_plugin_simple_block-1.0.1.dist-info/RECORD
