Metadata-Version: 2.1
Name: nonebot-plugin-simple-block
Version: 1.0.1
Summary: 屏蔽某个群聊或只相应某个群聊，方便开发者进行插件测试
Home-page: https://github.com/captain-wangrun-cn/nonebot-plugin-simple-block
License: GPL-3.0
Author: WR
Author-email: wangrun114514@foxmail.com
Requires-Python: >=3.9,<4.0
Classifier: License :: OSI Approved :: GNU General Public License v3 (GPLv3)
Classifier: Programming Language :: Python :: 3
Classifier: Programming Language :: Python :: 3.10
Classifier: Programming Language :: Python :: 3.9
Requires-Dist: nonebot-adapter-onebot (>=2.0.0,<3.0.0)
Requires-Dist: nonebot2 (>=2.2.0,<3.0.0)
Project-URL: Repository, https://github.com/captain-wangrun-cn/nonebot-plugin-simple-block
